sphinx_text_box/__init__.py
sphinx_text_box/text-box.py
sphinx_text_box-0.0.1.dist-info/LICENSE
sphinx_text_box-0.0.1.dist-info/WHEEL
sphinx_text_box-0.0.1.dist-info/METADATA
sphinx_text_box-0.0.1.dist-info/RECORD
